MANIFEST.in
README.md
UNLICENSE
setup.py
nosegrowl2/__init__.py
nosegrowl2/failure.png
nosegrowl2/start.png
nosegrowl2/success.png
nosegrowl2.egg-info/PKG-INFO
nosegrowl2.egg-info/SOURCES.txt
nosegrowl2.egg-info/dependency_links.txt
nosegrowl2.egg-info/entry_points.txt
nosegrowl2.egg-info/not-zip-safe
nosegrowl2.egg-info/requires.txt
nosegrowl2.egg-info/top_level.txt