Metadata-Version: 1.0
Name: nosegrowl2
Version: 0.3
Summary: A simple Nose plugin for Growl notifications.
Home-page: https://github.com/j4mie/nosegrowl2
Author: Jamie Matthews
Author-email: jamie.matthews@gmail.com
License: Public Domain
Platform: UNKNOWN
Classifier: Programming Language :: Python
Classifier: Development Status :: 3 - Alpha
Classifier: Intended Audience :: Developers
Classifier: License :: Public Domain
Classifier: Operating System :: MacOS :: MacOS X
Classifier: Topic :: Software Development :: Testing
